napari_morphodynamics/__init__.py
napari_morphodynamics/_version.py
napari_morphodynamics/base_plot.py
napari_morphodynamics/folder_list_widget.py
napari_morphodynamics/napari.yaml
napari_morphodynamics/napari_gui.py
napari_morphodynamics/_tests/__init__.py
napari_morphodynamics/_tests/test_widget.py
napari_morphodynamics-0.1.2.dist-info/LICENSE
napari_morphodynamics-0.1.2.dist-info/METADATA
napari_morphodynamics-0.1.2.dist-info/WHEEL
napari_morphodynamics-0.1.2.dist-info/entry_points.txt
napari_morphodynamics-0.1.2.dist-info/top_level.txt
napari_morphodynamics-0.1.2.dist-info/RECORD
