Metadata-Version: 2.1
Name: napari-morphodynamics
Version: 0.1.2
Summary: Interface to run the morphodynamics package.
Home-page: https://github.com/guiwitz/napari-morphodynamics
Author: Guillaume Witz
Author-email: guillaume.witz@unibe.ch
License: BSD-3-Clause
Project-URL: Bug Tracker, https://github.com/guiwitz/napari-morphodynamics/issues
Project-URL: Documentation, https://github.com/guiwitz/napari-morphodynamics#README.md
Project-URL: Source Code, https://github.com/guiwitz/napari-morphodynamics
Project-URL: User Support, https://github.com/guiwitz/napari-morphodynamics/issues
Classifier: Development Status :: 2 - Pre-Alpha
Classifier: Intended Audience :: Developers
Classifier: Framework :: napari
Classifier: Topic :: Software Development :: Testing
Classifier: Programming Language :: Python
Classifier: Programming Language :: Python :: 3
Classifier: Programming Language :: Python :: 3.9
Classifier: Programming Language :: Python :: 3.10
Classifier: Operating System :: OS Independent
Classifier: License :: OSI Approved :: BSD License
Requires-Python: >=3.9
License-File: LICENSE
Requires-Dist: morphodynamics
Requires-Dist: napari-convpaint
Requires-Dist: napari-guitils
Requires-Dist: napari-matplotlib
Provides-Extra: cellpose
Requires-Dist: cellpose ; extra == 'cellpose'
